Previous submissions/synchronizer/synchronizer.v
`timescale 1ns/1ps

module synchronizer(clk, Reprogram, Walk_Request, Sensor, Reset, Reset_Sync, Sensor_Sync, WR_Sync, Prog_Sync);
  
  input clk, Reprogram, Walk_Request, Sensor, Reset;
  output reg  Reset_Sync, Sensor_Sync, WR_Sync, Prog_Sync;
  
  always @(posedge clk)
    
    begin
      
      Reset_Sync = Reset;
      Sensor_Sync = Sensor;
      WR_Sync = Walk_Request;
      Prog_Sync = Reprogram;
      
    end
  
endmodule

Previous submissions/synchronizer/synchronizer_testbench.v
`timescale 1ns/1ps
`include "synchronizer.v"

module synchronizer_testbench;
  
  reg clk, Reprogram, Walk_Request, Sensor, Reset;
  wire Reset_Sync, Sensor_Sync, WR_Sync, Prog_Sync;
  
  synchronizer t1 (clk, Reprogram, Walk_Request, Sensor, Reset, Reset_Sync, Sensor_Sync, WR_Sync, Prog_Sync);
  
  initial begin
    
    $dumpfile("synchronizer.vcd");
    $dumpvars(0,synchronizer_testbench);
    
    clk = 0;
    Reset = 0;
    Sensor = 0;
    Walk_Request = 0;
    Reprogram = 0;
    
    
    #2 Reset = 1;
    #3 Reset = 0;
    
    #3 Walk_Request = 1;
    #5 Walk_Request = 0;
    
    #3 Sensor = 1 ;
    #6 Sensor = 0 ;
    
    #2 Reprogram = 1;
    #3 Reprogram = 0;
    
    #8 $finish();
    
  end
  
  initial forever #3 clk =~ clk; 
    
endmodule

Previous submissions/synchronizer/synchronizer.vcd
$date
	Tue May 25 00:19:10 2021
$end
$version
	Icarus Verilog
$end
$timescale
	1ps
$end
$scope module synchronizer_testbench $end
$var wire 1 ! WR_Sync $end
$var wire 1 " Sensor_Sync $end
$var wire 1 # Reset_Sync $end
$var wire 1 $ Prog_Sync $end
$var reg 1 % Reprogram $end
$var reg 1 & Reset $end
$var reg 1 ' Sensor $end
$var reg 1 ( Walk_Request $end
$var reg 1 ) clk $end
$scope module t1 $end
$var wire 1 % Reprogram $end
$var wire 1 & Reset $end
$var wire 1 ' Sensor $end
$var wire 1 ( Walk_Request $end
$var wire 1 ) clk $end
$var reg 1 $ Prog_Sync $end
$var reg 1 # Reset_Sync $end
$var reg 1 " Sensor_Sync $end
$var reg 1 ! WR_Sync $end
$upscope $end
$upscope $end
$enddefinitions $end
#0
$dumpvars
0)
0(
0'
0&
0%
x$
x#
x"
x!
$end
#2000
1&
#3000
0$
0!
0"
1#
1)
#5000
0&
#6000
0)
#8000
1(
#9000
1!
0#
1)
#12000
0)
#13000
0(
#15000
0!
1)
#16000
1'
#18000
0)
#21000
1"
1)
#22000
0'
#24000
1%
0)
#27000
0"
0%
1)
