Previous submissions/LED_lights/LED_lights.v
module LED_lights (LEDs, Rm,Ym,Gm,Rs,Ys,Gs,Walk);
  
  input[6:0] LEDs;
  output Rm,Ym,Gm,Rs,Ys,Gs,Walk;
  
  reg Rm,Ym,Gm,Rs,Ys,Gs,Walk;
  
  always @ (LEDs)
    begin
      Rm <= LEDs[6:6]; 
      Ym <= LEDs[5:5];
      Gm <= LEDs[4:4];
      Rs <= LEDs[3:3];
      Ys <= LEDs[2:2];
      Gs <= LEDs[1:1];
      Walk <= LEDs[0:0];
    end
endmodule

Previous submissions/LED_lights/LED_lights_testbench.v

`timescale 1ns/1ps
`include "LED_lights.v"

module LED_lights_test;
  
  reg [6:0] LEDs;
  wire Rm;
  wire Ym;
  wire Gm;
  wire Rs;
  wire Ys;
  wire Gs;
  wire Walk;
  
  LED_lights t1 (LEDs, Rm,Ym,Gm,Rs,Ys,Gs,Walk);
  
  initial begin
     
    $dumpfile("LED_lights.vcd");
    $dumpvars(0,LED_lights_test);
    
    LEDs = 0;
    #100;
    
    LEDs = 7'b1000000;
    #50;
    LEDs = 7'b0100000;
    #50;
    LEDs = 7'b0010000;
    #50;
    LEDs = 7'b0001000;
    #50;
    LEDs = 7'b0000100;
    #50;
    LEDs = 7'b0000010;
    #50;
    LEDs = 7'b0000001;
    
    #20 $finish();
    
  end
endmodule

Previous submissions/LED_lights/LED_lights.vcd
$date
	Mon May 24 23:47:49 2021
$end
$version
	Icarus Verilog
$end
$timescale
	1ps
$end
$scope module LED_lights_test $end
$var wire 1 ! Ys $end
$var wire 1 " Ym $end
$var wire 1 # Walk $end
$var wire 1 $ Rs $end
$var wire 1 % Rm $end
$var wire 1 & Gs $end
$var wire 1 ' Gm $end
$var reg 7 ( LEDs [6:0] $end
$scope module t1 $end
$var wire 7 ) LEDs [6:0] $end
$var reg 1 ' Gm $end
$var reg 1 & Gs $end
$var reg 1 % Rm $end
$var reg 1 $ Rs $end
$var reg 1 # Walk $end
$var reg 1 " Ym $end
$var reg 1 ! Ys $end
$upscope $end
$upscope $end
$enddefinitions $end
#0
$dumpvars
b0 )
b0 (
0'
0&
0%
0$
0#
0"
0!
$end
#100000
1%
b1000000 (
b1000000 )
#150000
1"
0%
b100000 (
b100000 )
#200000
1'
0"
b10000 (
b10000 )
#250000
1$
0'
b1000 (
b1000 )
#300000
1!
0$
b100 (
b100 )
#350000
1&
0!
b10 (
b10 )
#400000
1#
0&
b1 (
b1 )
