Previous submissions/Walk Register/Walk_Register.v
`timescale 1ns/1ps

module Walk_Register(clk, WR_Reset, Reset_Sync, WR_Sync, WR_Status);
  
  input clk, WR_Reset, Reset_Sync, WR_Sync;
  output reg WR_Status = 0 ;
  
  
  always @ (posedge clk)
    
    begin
      
      WR_Status <= (WR_Reset ||Reset_Sync) ? 0: WR_Status ? WR_Status : WR_Sync;
  
    end
  
  
endmodule

Previous submissions/Walk Register/Walk_Register_testbench.v
`timescale 1ns/1ps
`include "Walk_Register.v"

module Walk_Register_testbench;
  
  reg clk;
  reg WR_Sync;
  reg WR_Reset;
  reg Reset_Sync;
  
  wire WR_Status;
  
  Walk_Register t1 (clk, WR_Reset, Reset_Sync, WR_Sync, WR_Status);
  
  initial begin
    
    $dumpfile("Walk_Register.vcd");
    $dumpvars(0,Walk_Register_testbench);
    
    WR_Sync = 0;
    clk = 0;
    WR_Reset = 0;
    Reset_Sync = 0;
    
    #2 WR_Reset = 1;
    
    #2 WR_Sync = 1;
    
    #4
   
    WR_Reset = 0;
    WR_Sync = 1;
    
    #2 WR_Sync = 0;
    
    #2 WR_Reset = 1;
    
    #5 $finish();
    
  end
  
  initial begin
    
    forever #1 clk =~ clk;
    
  end
  
endmodule

Previous submissions/Walk Register/Walk_Register.vcd
$date
	Tue May 25 00:39:30 2021
$end
$version
	Icarus Verilog
$end
$timescale
	1ps
$end
$scope module Walk_Register_testbench $end
$var wire 1 ! WR_Status $end
$var reg 1 " Reset_Sync $end
$var reg 1 # WR_Reset $end
$var reg 1 $ WR_Sync $end
$var reg 1 % clk $end
$scope module t1 $end
$var wire 1 " Reset_Sync $end
$var wire 1 # WR_Reset $end
$var wire 1 $ WR_Sync $end
$var wire 1 % clk $end
$var reg 1 ! WR_Status $end
$upscope $end
$upscope $end
$enddefinitions $end
#0
$dumpvars
0%
0$
0#
0"
0!
$end
#1000
1%
#2000
0%
1#
#3000
1%
#4000
0%
1$
#5000
1%
#6000
0%
#7000
1%
#8000
0%
0#
#9000
1!
1%
#10000
0%
0$
#11000
1%
#12000
0%
1#
#13000
0!
1%
