Previous submissions/Divider/Divider.v
//divider timescale 1ms/1us
//divider timescale 1ns/1ps

//`timescale 1ms /1us
`timescale 1ns/1ps

module Divider(clk, divider_reset, Hz1_enable);
  
  input clk,divider_reset;
  output reg Hz1_enable = 0;
  
  //reg [9:0] count = 10'b0;
  reg [29:0] count = 30'b0;

  always @ (posedge clk)
    begin
      if (divider_reset == 1)
        //count = 10'b0;
        count = 30'b0;
      else
        count = count + 1;
      //Hz1_enable = count[9];
        Hz1_enable = count[29];
    end
  
endmodule

Previous submissions/Divider/Divider_testbench.v

//divider timescale 1ms/1us
//divider timescale 1ns/1ps

//timescale 1ms / 1us
`timescale 1ns/1ps
`include "Divider.v"

module Divider_testbench;
  
  reg clk;
  reg divider_reset;
  wire Hz1_enable;

  Divider t1 (clk, divider_reset, Hz1_enable);
    
  initial begin
    
    $dumpfile("Divider.vcd");
    $dumpvars(0,Divider_testbench);
    
    clk = 0;
    //divider_reset = 1;
    //#100
    divider_reset = 0;
    
    #4000
    divider_reset = 1;
    
    #100 $finish();
  end
  
  initial begin 
    forever #1 clk =~ clk; 
  end
  
endmodule

Previous submissions/Divider/Divider.vcd
$date
	Tue May 25 01:16:11 2021
$end
$version
	Icarus Verilog
$end
$timescale
	1ps
$end
$scope module Divider_testbench $end
$var wire 1 ! Hz1_enable $end
$var reg 1 " clk $end
$var reg 1 # divider_reset $end
$scope module t1 $end
$var wire 1 " clk $end
$var wire 1 # divider_reset $end
$var reg 1 ! Hz1_enable $end
$var reg 30 $ count [29:0] $end
$upscope $end
$upscope $end
$enddefinitions $end
#0
$dumpvars
b0 $
0#
0"
0!
$end
#1000
b1 $
1"
#2000
0"
#3000
b10 $
1"
#4000
0"
#5000
b11 $
1"
#6000
0"
#7000
b100 $
1"
#8000
0"
#9000
b101 $
1"
#10000
0"
#11000
b110 $
1"
#12000
0"
#13000
b111 $
1"
#14000
0"
#15000
b1000 $
1"
#16000
0"
#17000
b1001 $
1"
#18000
0"
#19000
b1010 $
1"
#20000
0"
#21000
b1011 $
1"
#22000
0"
#23000
b1100 $
1"
#24000
0"
#25000
b1101 $
1"
#26000
0"
#27000
b1110 $
1"
#28000
0"
#29000
b1111 $
1"
#30000
0"
#31000
b10000 $
1"
#32000
0"
#33000
b10001 $
1"
#34000
0"
#35000
b10010 $
1"
#36000
0"
#37000
b10011 $
1"
#38000
0"
#39000
b10100 $
1"
#40000
0"
#41000
b10101 $
1"
#42000
0"
#43000
b10110 $
1"
#44000
0"
#45000
b10111 $
1"
#46000
0"
#47000
b11000 $
1"
#48000
0"
#49000
b11001 $
1"
#50000
0"
#51000
b11010 $
1"
#52000
0"
#53000
b11011 $
1"
#54000
0"
#55000
b11100 $
1"
#56000
0"
#57000
b11101 $
1"
#58000
0"
#59000
b11110 $
1"
#60000
0"
#61000
b11111 $
1"
#62000
0"
#63000
b100000 $
1"
#64000
0"
#65000
b100001 $
1"
#66000
0"
#67000
b100010 $
1"
#68000
0"
#69000
b100011 $
1"
#70000
0"
#71000
b100100 $
1"
#72000
0"
#73000
b100101 $
1"
#74000
0"
#75000
b100110 $
1"
#76000
0"
#77000
b100111 $
1"
#78000
0"
#79000
b101000 $
1"
#80000
0"
#81000
b101001 $
1"
#82000
0"
#83000
b101010 $
1"
#84000
0"
#85000
b101011 $
1"
#86000
0"
#87000
b101100 $
1"
#88000
0"
#89000
b101101 $
1"
#90000
0"
#91000
b101110 $
1"
#92000
0"
#93000
b101111 $
1"
#94000
0"
#95000
b110000 $
1"
#96000
0"
#97000
b110001 $
1"
#98000
0"
#99000
b110010 $
1"
#100000
0"
#101000
b110011 $
1"
#102000
0"
#103000
b110100 $
1"
#104000
0"
#105000
b110101 $
1"
#106000
0"
#107000
b110110 $
1"
#108000
0"
#109000
b110111 $
1"
#110000
0"
#111000
b111000 $
1"
#112000
0"
#113000
b111001 $
1"
#114000
0"
#115000
b111010 $
1"
#116000
0"
#117000
b111011 $
1"
#118000
0"
#119000
b111100 $
1"
#120000
0"
#121000
b111101 $
1"
#122000
0"
#123000
b111110 $
1"
#124000
0"
#125000
b111111 $
1"
#126000
0"
#127000
b1000000 $
1"
#128000
0"
#129000
b1000001 $
1"
#130000
0"
#131000
b1000010 $
1"
#132000
0"
#133000
b1000011 $
1"
#134000
0"
#135000
b1000100 $
1"
#136000
0"
#137000
b1000101 $
1"
#138000
0"
#139000
b1000110 $
1"
#140000
0"
#141000
b1000111 $
1"
#142000
0"
#143000
b1001000 $
1"
#144000
0"
#145000
b1001001 $
1"
#146000
0"
#147000
b1001010 $
1"
#148000
0"
#149000
b1001011 $
1"
#150000
0"
#151000
b1001100 $
1"
#152000
0"
#153000
b1001101 $
1"
#154000
0"
#155000
b1001110 $
1"
#156000
0"
#157000
b1001111 $
1"
#158000
0"
#159000
b1010000 $
1"
#160000
0"
#161000
b1010001 $
1"
#162000
0"
#163000
b1010010 $
1"
#164000
0"
#165000
b1010011 $
1"
#166000
0"
#167000
b1010100 $
1"
#168000
0"
#169000
b1010101 $
1"
#170000
0"
#171000
b1010110 $
1"
#172000
0"
#173000
b1010111 $
1"
#174000
0"
#175000
b1011000 $
1"
#176000
0"
#177000
b1011001 $
1"
#178000
0"
#179000
b1011010 $
1"
#180000
0"
#181000
b1011011 $
1"
#182000
0"
#183000
b1011100 $
1"
#184000
0"
#185000
b1011101 $
1"
#186000
0"
#187000
b1011110 $
1"
#188000
0"
#189000
b1011111 $
1"
#190000
0"
#191000
b1100000 $
1"
#192000
0"
#193000
b1100001 $
1"
#194000
0"
#195000
b1100010 $
1"
#196000
0"
#197000
b1100011 $
1"
#198000
0"
#199000
b1100100 $
1"
#200000
0"
#201000
b1100101 $
1"
#202000
0"
#203000
b1100110 $
1"
#204000
0"
#205000
b1100111 $
1"
#206000
0"
#207000
b1101000 $
1"
#208000
0"
#209000
b1101001 $
1"
#210000
0"
#211000
b1101010 $
1"
#212000
0"
#213000
b1101011 $
1"
#214000
0"
#215000
b1101100 $
1"
#216000
0"
#217000
b1101101 $
1"
#218000
0"
#219000
b1101110 $
1"
#220000
0"
#221000
b1101111 $
1"
#222000
0"
#223000
b1110000 $
1"
#224000
0"
#225000
b1110001 $
1"
#226000
0"
#227000
b1110010 $
1"
#228000
0"
#229000
b1110011 $
1"
#230000
0"
#231000
b1110100 $
1"
#232000
0"
#233000
b1110101 $
1"
#234000
0"
#235000
b1110110 $
1"
#236000
0"
#237000
b1110111 $
1"
#238000
0"
#239000
b1111000 $
1"
#240000
0"
#241000
b1111001 $
1"
#242000
0"
#243000
b1111010 $
1"
#244000
0"
#245000
b1111011 $
1"
#246000
0"
#247000
b1111100 $
1"
#248000
0"
#249000
b1111101 $
1"
#250000
0"
#251000
b1111110 $
1"
#252000
0"
#253000
b1111111 $
1"
#254000
0"
#255000
b10000000 $
1"
#256000
0"
#257000
b10000001 $
1"
#258000
0"
#259000
b10000010 $
1"
#260000
0"
#261000
b10000011 $
1"
#262000
0"
#263000
b10000100 $
1"
#264000
0"
#265000
b10000101 $
1"
#266000
0"
#267000
b10000110 $
1"
#268000
0"
#269000
b10000111 $
1"
#270000
0"
#271000
b10001000 $
1"
#272000
0"
#273000
b10001001 $
1"
#274000
0"
#275000
b10001010 $
1"
#276000
0"
#277000
b10001011 $
1"
#278000
0"
#279000
b10001100 $
1"
#280000
0"
#281000
b10001101 $
1"
#282000
0"
#283000
b10001110 $
1"
#284000
0"
#285000
b10001111 $
1"
#286000
0"
#287000
b10010000 $
1"
#288000
0"
#289000
b10010001 $
1"
#290000
0"
#291000
b10010010 $
1"
#292000
0"
#293000
b10010011 $
1"
#294000
0"
#295000
b10010100 $
1"
#296000
0"
#297000
b10010101 $
1"
#298000
0"
#299000
b10010110 $
1"
#300000
0"
#301000
b10010111 $
1"
#302000
0"
#303000
b10011000 $
1"
#304000
0"
#305000
b10011001 $
1"
#306000
0"
#307000
b10011010 $
1"
#308000
0"
#309000
b10011011 $
1"
#310000
0"
#311000
b10011100 $
1"
#312000
0"
#313000
b10011101 $
1"
#314000
0"
#315000
b10011110 $
1"
#316000
0"
#317000
b10011111 $
1"
#318000
0"
#319000
b10100000 $
1"
#320000
0"
#321000
b10100001 $
1"
#322000
0"
#323000
b10100010 $
1"
#324000
0"
#325000
b10100011 $
1"
#326000
0"
#327000
b10100100 $
1"
#328000
0"
#329000
b10100101 $
1"
#330000
0"
#331000
b10100110 $
1"
#332000
0"
#333000
b10100111 $
1"
#334000
0"
#335000
b10101000 $
1"
#336000
0"
#337000
b10101001 $
1"
#338000
0"
#339000
b10101010 $
1"
#340000
0"
#341000
b10101011 $
1"
#342000
0"
#343000
b10101100 $
1"
#344000
0"
#345000
b10101101 $
1"
#346000
0"
#347000
b10101110 $
1"
#348000
0"
#349000
b10101111 $
1"
#350000
0"
#351000
b10110000 $
1"
#352000
0"
#353000
b10110001 $
1"
#354000
0"
#355000
b10110010 $
1"
#356000
0"
#357000
b10110011 $
1"
#358000
0"
#359000
b10110100 $
1"
#360000
0"
#361000
b10110101 $
1"
#362000
0"
#363000
b10110110 $
1"
#364000
0"
#365000
b10110111 $
1"
#366000
0"
#367000
b10111000 $
1"
#368000
0"
#369000
b10111001 $
1"
#370000
0"
#371000
b10111010 $
1"
#372000
0"
#373000
b10111011 $
1"
#374000
0"
#375000
b10111100 $
1"
#376000
0"
#377000
b10111101 $
1"
#378000
0"
#379000
b10111110 $
1"
#380000
0"
#381000
b10111111 $
1"
#382000
0"
#383000
b11000000 $
1"
#384000
0"
#385000
b11000001 $
1"
#386000
0"
#387000
b11000010 $
1"
#388000
0"
#389000
b11000011 $
1"
#390000
0"
#391000
b11000100 $
1"
#392000
0"
#393000
b11000101 $
1"
#394000
0"
#395000
b11000110 $
1"
#396000
0"
#397000
b11000111 $
1"
#398000
0"
#399000
b11001000 $
1"
#400000
0"
#401000
b11001001 $
1"
#402000
0"
#403000
b11001010 $
1"
#404000
0"
#405000
b11001011 $
1"
#406000
0"
#407000
b11001100 $
1"
#408000
0"
#409000
b11001101 $
1"
#410000
0"
#411000
b11001110 $
1"
#412000
0"
#413000
b11001111 $
1"
#414000
0"
#415000
b11010000 $
1"
#416000
0"
#417000
b11010001 $
1"
#418000
0"
#419000
b11010010 $
1"
#420000
0"
#421000
b11010011 $
1"
#422000
0"
#423000
b11010100 $
1"
#424000
0"
#425000
b11010101 $
1"
#426000
0"
#427000
b11010110 $
1"
#428000
0"
#429000
b11010111 $
1"
#430000
0"
#431000
b11011000 $
1"
#432000
0"
#433000
b11011001 $
1"
#434000
0"
#435000
b11011010 $
1"
#436000
0"
#437000
b11011011 $
1"
#438000
0"
#439000
b11011100 $
1"
#440000
0"
#441000
b11011101 $
1"
#442000
0"
#443000
b11011110 $
1"
#444000
0"
#445000
b11011111 $
1"
#446000
0"
#447000
b11100000 $
1"
#448000
0"
#449000
b11100001 $
1"
#450000
0"
#451000
b11100010 $
1"
#452000
0"
#453000
b11100011 $
1"
#454000
0"
#455000
b11100100 $
1"
#456000
0"
#457000
b11100101 $
1"
#458000
0"
#459000
b11100110 $
1"
#460000
0"
#461000
b11100111 $
1"
#462000
0"
#463000
b11101000 $
1"
#464000
0"
#465000
b11101001 $
1"
#466000
0"
#467000
b11101010 $
1"
#468000
0"
#469000
b11101011 $
1"
#470000
0"
#471000
b11101100 $
1"
#472000
0"
#473000
b11101101 $
1"
#474000
0"
#475000
b11101110 $
1"
#476000
0"
#477000
b11101111 $
1"
#478000
0"
#479000
b11110000 $
1"
#480000
0"
#481000
b11110001 $
1"
#482000
0"
#483000
b11110010 $
1"
#484000
0"
#485000
b11110011 $
1"
#486000
0"
#487000
b11110100 $
1"
#488000
0"
#489000
b11110101 $
1"
#490000
0"
#491000
b11110110 $
1"
#492000
0"
#493000
b11110111 $
1"
#494000
0"
#495000
b11111000 $
1"
#496000
0"
#497000
b11111001 $
1"
#498000
0"
#499000
b11111010 $
1"
#500000
0"
#501000
b11111011 $
1"
#502000
0"
#503000
b11111100 $
1"
#504000
0"
#505000
b11111101 $
1"
#506000
0"
#507000
b11111110 $
1"
#508000
0"
#509000
b11111111 $
1"
#510000
0"
#511000
b100000000 $
1"
#512000
0"
#513000
b100000001 $
1"
#514000
0"
#515000
b100000010 $
1"
#516000
0"
#517000
b100000011 $
1"
#518000
0"
#519000
b100000100 $
1"
#520000
0"
#521000
b100000101 $
1"
#522000
0"
#523000
b100000110 $
1"
#524000
0"
#525000
b100000111 $
1"
#526000
0"
#527000
b100001000 $
1"
#528000
0"
#529000
b100001001 $
1"
#530000
0"
#531000
b100001010 $
1"
#532000
0"
#533000
b100001011 $
1"
#534000
0"
#535000
b100001100 $
1"
#536000
0"
#537000
b100001101 $
1"
#538000
0"
#539000
b100001110 $
1"
#540000
0"
#541000
b100001111 $
1"
#542000
0"
#543000
b100010000 $
1"
#544000
0"
#545000
b100010001 $
1"
#546000
0"
#547000
b100010010 $
1"
#548000
0"
#549000
b100010011 $
1"
#550000
0"
#551000
b100010100 $
1"
#552000
0"
#553000
b100010101 $
1"
#554000
0"
#555000
b100010110 $
1"
#556000
0"
#557000
b100010111 $
1"
#558000
0"
#559000
b100011000 $
1"
#560000
0"
#561000
b100011001 $
1"
#562000
0"
#563000
b100011010 $
1"
#564000
0"
#565000
b100011011 $
1"
#566000
0"
#567000
b100011100 $
1"
#568000
0"
#569000
b100011101 $
1"
#570000
0"
#571000
b100011110 $
1"
#572000
0"
#573000
b100011111 $
1"
#574000
0"
#575000
b100100000 $
1"
#576000
0"
#577000
b100100001 $
1"
#578000
0"
#579000
b100100010 $
1"
#580000
0"
#581000
b100100011 $
1"
#582000
0"
#583000
b100100100 $
1"
#584000
0"
#585000
b100100101 $
1"
#586000
0"
#587000
b100100110 $
1"
#588000
0"
#589000
b100100111 $
1"
#590000
0"
#591000
b100101000 $
1"
#592000
0"
#593000
b100101001 $
1"
#594000
0"
#595000
b100101010 $
1"
#596000
0"
#597000
b100101011 $
1"
#598000
0"
#599000
b100101100 $
1"
#600000
0"
#601000
b100101101 $
1"
#602000
0"
#603000
b100101110 $
1"
#604000
0"
#605000
b100101111 $
1"
#606000
0"
#607000
b100110000 $
1"
#608000
0"
#609000
b100110001 $
1"
#610000
0"
#611000
b100110010 $
1"
#612000
0"
#613000
b100110011 $
1"
#614000
0"
#615000
b100110100 $
1"
#616000
0"
#617000
b100110101 $
1"
#618000
0"
#619000
b100110110 $
1"
#620000
0"
#621000
b100110111 $
1"
#622000
0"
#623000
b100111000 $
1"
#624000
0"
#625000
b100111001 $
1"
#626000
0"
#627000
b100111010 $
1"
#628000
0"
#629000
b100111011 $
1"
#630000
0"
#631000
b100111100 $
1"
#632000
0"
#633000
b100111101 $
1"
#634000
0"
#635000
b100111110 $
1"
#636000
0"
#637000
b100111111 $
1"
#638000
0"
#639000
b101000000 $
1"
#640000
0"
#641000
b101000001 $
1"
#642000
0"
#643000
b101000010 $
1"
#644000
0"
#645000
b101000011 $
1"
#646000
0"
#647000
b101000100 $
1"
#648000
0"
#649000
b101000101 $
1"
#650000
0"
#651000
b101000110 $
1"
#652000
0"
#653000
b101000111 $
1"
#654000
0"
#655000
b101001000 $
1"
#656000
0"
#657000
b101001001 $
1"
#658000
0"
#659000
b101001010 $
1"
#660000
0"
#661000
b101001011 $
1"
#662000
0"
#663000
b101001100 $
1"
#664000
0"
#665000
b101001101 $
1"
#666000
0"
#667000
b101001110 $
1"
#668000
0"
#669000
b101001111 $
1"
#670000
0"
#671000
b101010000 $
1"
#672000
0"
#673000
b101010001 $
1"
#674000
0"
#675000
b101010010 $
1"
#676000
0"
#677000
b101010011 $
1"
#678000
0"
#679000
b101010100 $
1"
#680000
0"
#681000
b101010101 $
1"
#682000
0"
#683000
b101010110 $
1"
#684000
0"
#685000
b101010111 $
1"
#686000
0"
#687000
b101011000 $
1"
#688000
0"
#689000
b101011001 $
1"
#690000
0"
#691000
b101011010 $
1"
#692000
0"
#693000
b101011011 $
1"
#694000
0"
#695000
b101011100 $
1"
#696000
0"
#697000
b101011101 $
1"
#698000
0"
#699000
b101011110 $
1"
#700000
0"
#701000
b101011111 $
1"
#702000
0"
#703000
b101100000 $
1"
#704000
0"
#705000
b101100001 $
1"
#706000
0"
#707000
b101100010 $
1"
#708000
0"
#709000
b101100011 $
1"
#710000
0"
#711000
b101100100 $
1"
#712000
0"
#713000
b101100101 $
1"
#714000
0"
#715000
b101100110 $
1"
#716000
0"
#717000
b101100111 $
1"
#718000
0"
#719000
b101101000 $
1"
#720000
0"
#721000
b101101001 $
1"
#722000
0"
#723000
b101101010 $
1"
#724000
0"
#725000
b101101011 $
1"
#726000
0"
#727000
b101101100 $
1"
#728000
0"
#729000
b101101101 $
1"
#730000
0"
#731000
b101101110 $
1"
#732000
0"
#733000
b101101111 $
1"
#734000
0"
#735000
b101110000 $
1"
#736000
0"
#737000
b101110001 $
1"
#738000
0"
#739000
b101110010 $
1"
#740000
0"
#741000
b101110011 $
1"
#742000
0"
#743000
b101110100 $
1"
#744000
0"
#745000
b101110101 $
1"
#746000
0"
#747000
b101110110 $
1"
#748000
0"
#749000
b101110111 $
1"
#750000
0"
#751000
b101111000 $
1"
#752000
0"
#753000
b101111001 $
1"
#754000
0"
#755000
b101111010 $
1"
#756000
0"
#757000
b101111011 $
1"
#758000
0"
#759000
b101111100 $
1"
#760000
0"
#761000
b101111101 $
1"
#762000
0"
#763000
b101111110 $
1"
#764000
0"
#765000
b101111111 $
1"
#766000
0"
#767000
b110000000 $
1"
#768000
0"
#769000
b110000001 $
1"
#770000
0"
#771000
b110000010 $
1"
#772000
0"
#773000
b110000011 $
1"
#774000
0"
#775000
b110000100 $
1"
#776000
0"
#777000
b110000101 $
1"
#778000
0"
#779000
b110000110 $
1"
#780000
0"
#781000
b110000111 $
1"
#782000
0"
#783000
b110001000 $
1"
#784000
0"
#785000
b110001001 $
1"
#786000
0"
#787000
b110001010 $
1"
#788000
0"
#789000
b110001011 $
1"
#790000
0"
#791000
b110001100 $
1"
#792000
0"
#793000
b110001101 $
1"
#794000
0"
#795000
b110001110 $
1"
#796000
0"
#797000
b110001111 $
1"
#798000
0"
#799000
b110010000 $
1"
#800000
0"
#801000
b110010001 $
1"
#802000
0"
#803000
b110010010 $
1"
#804000
0"
#805000
b110010011 $
1"
#806000
0"
#807000
b110010100 $
1"
#808000
0"
#809000
b110010101 $
1"
#810000
0"
#811000
b110010110 $
1"
#812000
0"
#813000
b110010111 $
1"
#814000
0"
#815000
b110011000 $
1"
#816000
0"
#817000
b110011001 $
1"
#818000
0"
#819000
b110011010 $
1"
#820000
0"
#821000
b110011011 $
1"
#822000
0"
#823000
b110011100 $
1"
#824000
0"
#825000
b110011101 $
1"
#826000
0"
#827000
b110011110 $
1"
#828000
0"
#829000
b110011111 $
1"
#830000
0"
#831000
b110100000 $
1"
#832000
0"
#833000
b110100001 $
1"
#834000
0"
#835000
b110100010 $
1"
#836000
0"
#837000
b110100011 $
1"
#838000
0"
#839000
b110100100 $
1"
#840000
0"
#841000
b110100101 $
1"
#842000
0"
#843000
b110100110 $
1"
#844000
0"
#845000
b110100111 $
1"
#846000
0"
#847000
b110101000 $
1"
#848000
0"
#849000
b110101001 $
1"
#850000
0"
#851000
b110101010 $
1"
#852000
0"
#853000
b110101011 $
1"
#854000
0"
#855000
b110101100 $
1"
#856000
0"
#857000
b110101101 $
1"
#858000
0"
#859000
b110101110 $
1"
#860000
0"
#861000
b110101111 $
1"
#862000
0"
#863000
b110110000 $
1"
#864000
0"
#865000
b110110001 $
1"
#866000
0"
#867000
b110110010 $
1"
#868000
0"
#869000
b110110011 $
1"
#870000
0"
#871000
b110110100 $
1"
#872000
0"
#873000
b110110101 $
1"
#874000
0"
#875000
b110110110 $
1"
#876000
0"
#877000
b110110111 $
1"
#878000
0"
#879000
b110111000 $
1"
#880000
0"
#881000
b110111001 $
1"
#882000
0"
#883000
b110111010 $
1"
#884000
0"
#885000
b110111011 $
1"
#886000
0"
#887000
b110111100 $
1"
#888000
0"
#889000
b110111101 $
1"
#890000
0"
#891000
b110111110 $
1"
#892000
0"
#893000
b110111111 $
1"
#894000
0"
#895000
b111000000 $
1"
#896000
0"
#897000
b111000001 $
1"
#898000
0"
#899000
b111000010 $
1"
#900000
0"
#901000
b111000011 $
1"
#902000
0"
#903000
b111000100 $
1"
#904000
0"
#905000
b111000101 $
1"
#906000
0"
#907000
b111000110 $
1"
#908000
0"
#909000
b111000111 $
1"
#910000
0"
#911000
b111001000 $
1"
#912000
0"
#913000
b111001001 $
1"
#914000
0"
#915000
b111001010 $
1"
#916000
0"
#917000
b111001011 $
1"
#918000
0"
#919000
b111001100 $
1"
#920000
0"
#921000
b111001101 $
1"
#922000
0"
#923000
b111001110 $
1"
#924000
0"
#925000
b111001111 $
1"
#926000
0"
#927000
b111010000 $
1"
#928000
0"
#929000
b111010001 $
1"
#930000
0"
#931000
b111010010 $
1"
#932000
0"
#933000
b111010011 $
1"
#934000
0"
#935000
b111010100 $
1"
#936000
0"
#937000
b111010101 $
1"
#938000
0"
#939000
b111010110 $
1"
#940000
0"
#941000
b111010111 $
1"
#942000
0"
#943000
b111011000 $
1"
#944000
0"
#945000
b111011001 $
1"
#946000
0"
#947000
b111011010 $
1"
#948000
0"
#949000
b111011011 $
1"
#950000
0"
#951000
b111011100 $
1"
#952000
0"
#953000
b111011101 $
1"
#954000
0"
#955000
b111011110 $
1"
#956000
0"
#957000
b111011111 $
1"
#958000
0"
#959000
b111100000 $
1"
#960000
0"
#961000
b111100001 $
1"
#962000
0"
#963000
b111100010 $
1"
#964000
0"
#965000
b111100011 $
1"
#966000
0"
#967000
b111100100 $
1"
#968000
0"
#969000
b111100101 $
1"
#970000
0"
#971000
b111100110 $
1"
#972000
0"
#973000
b111100111 $
1"
#974000
0"
#975000
b111101000 $
1"
#976000
0"
#977000
b111101001 $
1"
#978000
0"
#979000
b111101010 $
1"
#980000
0"
#981000
b111101011 $
1"
#982000
0"
#983000
b111101100 $
1"
#984000
0"
#985000
b111101101 $
1"
#986000
0"
#987000
b111101110 $
1"
#988000
0"
#989000
b111101111 $
1"
#990000
0"
#991000
b111110000 $
1"
#992000
0"
#993000
b111110001 $
1"
#994000
0"
#995000
b111110010 $
1"
#996000
0"
#997000
b111110011 $
1"
#998000
0"
#999000
b111110100 $
1"
#1000000
0"
#1001000
b111110101 $
1"
#1002000
0"
#1003000
b111110110 $
1"
#1004000
0"
#1005000
b111110111 $
1"
#1006000
0"
#1007000
b111111000 $
1"
#1008000
0"
#1009000
b111111001 $
1"
#1010000
0"
#1011000
b111111010 $
1"
#1012000
0"
#1013000
b111111011 $
1"
#1014000
0"
#1015000
b111111100 $
1"
#1016000
0"
#1017000
b111111101 $
1"
#1018000
0"
#1019000
b111111110 $
1"
#1020000
0"
#1021000
b111111111 $
1"
#1022000
0"
#1023000
b1000000000 $
1"
#1024000
0"
#1025000
b1000000001 $
1"
#1026000
0"
#1027000
b1000000010 $
1"
#1028000
0"
#1029000
b1000000011 $
1"
#1030000
0"
#1031000
b1000000100 $
1"
#1032000
0"
#1033000
b1000000101 $
1"
#1034000
0"
#1035000
b1000000110 $
1"
#1036000
0"
#1037000
b1000000111 $
1"
#1038000
0"
#1039000
b1000001000 $
1"
#1040000
0"
#1041000
b1000001001 $
1"
#1042000
0"
#1043000
b1000001010 $
1"
#1044000
0"
#1045000
b1000001011 $
1"
#1046000
0"
#1047000
b1000001100 $
1"
#1048000
0"
#1049000
b1000001101 $
1"
#1050000
0"
#1051000
b1000001110 $
1"
#1052000
0"
#1053000
b1000001111 $
1"
#1054000
0"
#1055000
b1000010000 $
1"
#1056000
0"
#1057000
b1000010001 $
1"
#1058000
0"
#1059000
b1000010010 $
1"
#1060000
0"
#1061000
b1000010011 $
1"
#1062000
0"
#1063000
b1000010100 $
1"
#1064000
0"
#1065000
b1000010101 $
1"
#1066000
0"
#1067000
b1000010110 $
1"
#1068000
0"
#1069000
b1000010111 $
1"
#1070000
0"
#1071000
b1000011000 $
1"
#1072000
0"
#1073000
b1000011001 $
1"
#1074000
0"
#1075000
b1000011010 $
1"
#1076000
0"
#1077000
b1000011011 $
1"
#1078000
0"
#1079000
b1000011100 $
1"
#1080000
0"
#1081000
b1000011101 $
1"
#1082000
0"
#1083000
b1000011110 $
1"
#1084000
0"
#1085000
b1000011111 $
1"
#1086000
0"
#1087000
b1000100000 $
1"
#1088000
0"
#1089000
b1000100001 $
1"
#1090000
0"
#1091000
b1000100010 $
1"
#1092000
0"
#1093000
b1000100011 $
1"
#1094000
0"
#1095000
b1000100100 $
1"
#1096000
0"
#1097000
b1000100101 $
1"
#1098000
0"
#1099000
b1000100110 $
1"
#1100000
0"
#1101000
b1000100111 $
1"
#1102000
0"
#1103000
b1000101000 $
1"
#1104000
0"
#1105000
b1000101001 $
1"
#1106000
0"
#1107000
b1000101010 $
1"
#1108000
0"
#1109000
b1000101011 $
1"
#1110000
0"
#1111000
b1000101100 $
1"
#1112000
0"
#1113000
b1000101101 $
1"
#1114000
0"
#1115000
b1000101110 $
1"
#1116000
0"
#1117000
b1000101111 $
1"
#1118000
0"
#1119000
b1000110000 $
1"
#1120000
0"
#1121000
b1000110001 $
1"
#1122000
0"
#1123000
b1000110010 $
1"
#1124000
0"
#1125000
b1000110011 $
1"
#1126000
0"
#1127000
b1000110100 $
1"
#1128000
0"
#1129000
b1000110101 $
1"
#1130000
0"
#1131000
b1000110110 $
1"
#1132000
0"
#1133000
b1000110111 $
1"
#1134000
0"
#1135000
b1000111000 $
1"
#1136000
0"
#1137000
b1000111001 $
1"
#1138000
0"
#1139000
b1000111010 $
1"
#1140000
0"
#1141000
b1000111011 $
1"
#1142000
0"
#1143000
b1000111100 $
1"
#1144000
0"
#1145000
b1000111101 $
1"
#1146000
0"
#1147000
b1000111110 $
1"
#1148000
0"
#1149000
b1000111111 $
1"
#1150000
0"
#1151000
b1001000000 $
1"
#1152000
0"
#1153000
b1001000001 $
1"
#1154000
0"
#1155000
b1001000010 $
1"
#1156000
0"
#1157000
b1001000011 $
1"
#1158000
0"
#1159000
b1001000100 $
1"
#1160000
0"
#1161000
b1001000101 $
1"
#1162000
0"
#1163000
b1001000110 $
1"
#1164000
0"
#1165000
b1001000111 $
1"
#1166000
0"
#1167000
b1001001000 $
1"
#1168000
0"
#1169000
b1001001001 $
1"
#1170000
0"
#1171000
b1001001010 $
1"
#1172000
0"
#1173000
b1001001011 $
1"
#1174000
0"
#1175000
b1001001100 $
1"
#1176000
0"
#1177000
b1001001101 $
1"
#1178000
0"
#1179000
b1001001110 $
1"
#1180000
0"
#1181000
b1001001111 $
1"
#1182000
0"
#1183000
b1001010000 $
1"
#1184000
0"
#1185000
b1001010001 $
1"
#1186000
0"
#1187000
b1001010010 $
1"
#1188000
0"
#1189000
b1001010011 $
1"
#1190000
0"
#1191000
b1001010100 $
1"
#1192000
0"
#1193000
b1001010101 $
1"
#1194000
0"
#1195000
b1001010110 $
1"
#1196000
0"
#1197000
b1001010111 $
1"
#1198000
0"
#1199000
b1001011000 $
1"
#1200000
0"
#1201000
b1001011001 $
1"
#1202000
0"
#1203000
b1001011010 $
1"
#1204000
0"
#1205000
b1001011011 $
1"
#1206000
0"
#1207000
b1001011100 $
1"
#1208000
0"
#1209000
b1001011101 $
1"
#1210000
0"
#1211000
b1001011110 $
1"
#1212000
0"
#1213000
b1001011111 $
1"
#1214000
0"
#1215000
b1001100000 $
1"
#1216000
0"
#1217000
b1001100001 $
1"
#1218000
0"
#1219000
b1001100010 $
1"
#1220000
0"
#1221000
b1001100011 $
1"
#1222000
0"
#1223000
b1001100100 $
1"
#1224000
0"
#1225000
b1001100101 $
1"
#1226000
0"
#1227000
b1001100110 $
1"
#1228000
0"
#1229000
b1001100111 $
1"
#1230000
0"
#1231000
b1001101000 $
1"
#1232000
0"
#1233000
b1001101001 $
1"
#1234000
0"
#1235000
b1001101010 $
1"
#1236000
0"
#1237000
b1001101011 $
1"
#1238000
0"
#1239000
b1001101100 $
1"
#1240000
0"
#1241000
b1001101101 $
1"
#1242000
0"
#1243000
b1001101110 $
1"
#1244000
0"
#1245000
b1001101111 $
1"
#1246000
0"
#1247000
b1001110000 $
1"
#1248000
0"
#1249000
b1001110001 $
1"
#1250000
0"
#1251000
b1001110010 $
1"
#1252000
0"
#1253000
b1001110011 $
1"
#1254000
0"
#1255000
b1001110100 $
1"
#1256000
0"
#1257000
b1001110101 $
1"
#1258000
0"
#1259000
b1001110110 $
1"
#1260000
0"
#1261000
b1001110111 $
1"
#1262000
0"
#1263000
b1001111000 $
1"
#1264000
0"
#1265000
b1001111001 $
1"
#1266000
0"
#1267000
b1001111010 $
1"
#1268000
0"
#1269000
b1001111011 $
1"
#1270000
0"
#1271000
b1001111100 $
1"
#1272000
0"
#1273000
b1001111101 $
1"
#1274000
0"
#1275000
b1001111110 $
1"
#1276000
0"
#1277000
b1001111111 $
1"
#1278000
0"
#1279000
b1010000000 $
1"
#1280000
0"
#1281000
b1010000001 $
1"
#1282000
0"
#1283000
b1010000010 $
1"
#1284000
0"
#1285000
b1010000011 $
1"
#1286000
0"
#1287000
b1010000100 $
1"
#1288000
0"
#1289000
b1010000101 $
1"
#1290000
0"
#1291000
b1010000110 $
1"
#1292000
0"
#1293000
b1010000111 $
1"
#1294000
0"
#1295000
b1010001000 $
1"
#1296000
0"
#1297000
b1010001001 $
1"
#1298000
0"
#1299000
b1010001010 $
1"
#1300000
0"
#1301000
b1010001011 $
1"
#1302000
0"
#1303000
b1010001100 $
1"
#1304000
0"
#1305000
b1010001101 $
1"
#1306000
0"
#1307000
b1010001110 $
1"
#1308000
0"
#1309000
b1010001111 $
1"
#1310000
0"
#1311000
b1010010000 $
1"
#1312000
0"
