Full design/fulldesign.v
//`timescale 1ms / 1ms

//////////////////////////////////////////////////////////////////////////////////
//////////////             E/15/335 - fulldesign                 /////////////////
//////////////     EE587 : Digital System Design and Synthesis   /////////////////
//////////////                 Assignment                        /////////////////
//////////////////////////////////////////////////////////////////////////////////

////////////////////////////////////////////
////////       FSM        //////////////////
////////////////////////////////////////////
module FSM(Sensor_Sync, WR_Status, Prog_Sync, expired, WR_Reset, interval, start_timer, LEDs, clk, Reset_Sync);
	
    input Sensor_Sync, WR_Status, expired, clk, Reset_Sync;
	input [3:0] Prog_Sync;
	output WR_Reset, start_timer;
    output[6:0] LEDs;
	output[1:0] interval;
	
	reg WR_Reset, start_timer;
    reg[6:0] LEDs;
    reg[1:0] interval = 2'b00;
	reg[2:0] state = 3'd0;
	
	parameter START_MAIN_GREEN = 0;
	parameter CONT_MAIN_GREEN_NO_TRAFFIC = 1;
	parameter CONT_MAIN_GREEN_TRAFFIC = 2;
	parameter MAIN_YELLOW = 3;
	parameter PEDESTRIAN_WALK = 4;
	parameter START_SIDE_GREEN = 5;
	parameter CONT_SIDE_GREEN_TRAFFIC = 6;
	parameter SIDE_YELLOW = 7;

	parameter BASE_ADD = 2'b00 ;
	parameter EXT_ADD = 2'b01 ;
	parameter YEL_ADD = 2'b10 ;
	
	always @ ( posedge clk,Reset_Sync,negedge clk )
	begin
	
		start_timer = 0;					
		WR_Reset = 0;

      if ( Reset_Sync || Prog_Sync)
			begin
			start_timer = 1;
			interval <= BASE_ADD ;
			state <= START_MAIN_GREEN ;
			end
			
		else if (~ expired )
			begin
			case ( state )
				START_MAIN_GREEN, CONT_MAIN_GREEN_NO_TRAFFIC, CONT_MAIN_GREEN_TRAFFIC :
					LEDs <= 7'b0011000;	// bits represent Rm,Ym,Gm,Rs,Ys,Gs,Walk from left to right of the bits 
            
				MAIN_YELLOW :
					LEDs <= 7'b0101000;	

				PEDESTRIAN_WALK :
					LEDs <= 7'b1001001;	 

				START_SIDE_GREEN, CONT_SIDE_GREEN_TRAFFIC :
					LEDs <= 7'b1000010;	

				SIDE_YELLOW :
					LEDs <= 7'b1000100;	
			endcase
			end
		
		else
			begin
			
			start_timer = 1;

			case ( state )
				START_MAIN_GREEN :
					begin
                      if ( Sensor_Sync )
							begin
								
								interval <= EXT_ADD ;
								state <= CONT_MAIN_GREEN_TRAFFIC ;
							end
						else
							begin
								interval <= BASE_ADD ;
								state <= CONT_MAIN_GREEN_NO_TRAFFIC ;
							end
					end

				CONT_MAIN_GREEN_NO_TRAFFIC,CONT_MAIN_GREEN_TRAFFIC :
					begin
						interval <= YEL_ADD ;
						state <= MAIN_YELLOW ;
					end

				MAIN_YELLOW :
					begin
						
                      if ( WR_Status )
							begin
								
								interval <= EXT_ADD ;
								state <= PEDESTRIAN_WALK ;
							end
						else
							begin
								interval <= BASE_ADD ;
								state <= START_SIDE_GREEN ;
							end
					end

				PEDESTRIAN_WALK :
					begin
				
						interval <= BASE_ADD ;
						state <= START_SIDE_GREEN ;
						WR_Reset = 1;
					end

				START_SIDE_GREEN :
					begin
                      if ( Sensor_Sync )
							begin
								interval <= EXT_ADD ;
								state <= CONT_SIDE_GREEN_TRAFFIC ;
							end
						else
							begin
								interval <= YEL_ADD ;
								state  <= SIDE_YELLOW ;

							end
					end

				CONT_SIDE_GREEN_TRAFFIC :
					begin
						interval <= YEL_ADD ;
						state <= SIDE_YELLOW ;
					end

				SIDE_YELLOW :
					begin
						interval <= BASE_ADD ;
						state <= START_MAIN_GREEN ;
					end

			endcase
			end
			
	end
	
endmodule


////////////////////////////////////////////////////////
///////////////// LED_lights ///////////////////////////
////////////////////////////////////////////////////////

module LED_lights (LEDs, Rm,Ym,Gm,Rs,Ys,Gs,Walk);
  
  input[6:0] LEDs;
  output Rm,Ym,Gm,Rs,Ys,Gs,Walk;
  
  reg Rm,Ym,Gm,Rs,Ys,Gs,Walk;
  
  always @ (LEDs)
    begin
      Rm <= LEDs[6:6]; 
      Ym <= LEDs[5:5];
      Gm <= LEDs[4:4];
      Rs <= LEDs[3:3];
      Ys <= LEDs[2:2];
      Gs <= LEDs[1:1];
      Walk <= LEDs[0:0];
    end
endmodule

module Divider(clk, Hz1_enable);
  
  input clk;
  output reg Hz1_enable = 0;
  reg [9:0] counter = 10'b0;

  always @ (negedge clk, posedge clk)
  begin
      if (counter != 10'b1111101000) begin
          counter = counter + 1;
      end

      else begin
          Hz1_enable =~ Hz1_enable;
          counter = 1;
      end
  end
endmodule

////////////////////////////////////////////////////////////////
///////////////  synchronizer  /////////////////////////////////
////////////////////////////////////////////////////////////////

module synchronizer(clk, Reprogram, Walk_Request, Sensor, Reset, Reset_Sync, Sensor_Sync, WR_Sync, Prog_Sync);
  
  input clk, Reprogram, Walk_Request, Sensor, Reset;
  output reg  Reset_Sync, Sensor_Sync, WR_Sync;
  output reg [3:0] Prog_Sync;
  
  always @(posedge clk)
    
    begin
      
      Reset_Sync = Reset;
      Sensor_Sync = Sensor;
      WR_Sync = Walk_Request;
      Prog_Sync = Reprogram;
      
    end
  
endmodule


////////////////////////////////////////////////////////////////////
//////////////   TimeParameters   //////////////////////////////////
////////////////////////////////////////////////////////////////////


module TimeParameters(selector, interval, Prog_Sync,time_value, value, clk, Reset_Sync);
	 
  
    input clk, Reset_Sync;
	input[1:0] selector;
	input[3:0] Prog_Sync;
	input[1:0] interval;
    input[3:0] time_value;
    output reg[3:0] value;
	
	parameter BASE_ADD = 2'b00;
	parameter EXTD_ADD = 2'b01;
	parameter YELL_ADD = 2'b10;
	
	parameter BASE_DEFAULT = 4'd6;
	parameter EXTD_DEFAULT = 4'd3;
	parameter YELL_DEFAULT = 4'd2;
	
	reg[3:0] BASE_VALUE = BASE_DEFAULT;
	reg[3:0] EXTD_VALUE = EXTD_DEFAULT;
	reg[3:0] YELL_VALUE = YELL_DEFAULT;
		

	always @ (posedge clk)
	begin
      if(Reset_Sync)
			begin
				BASE_VALUE = BASE_DEFAULT;
				EXTD_VALUE = EXTD_DEFAULT;
				YELL_VALUE = YELL_DEFAULT;
			end
			
      else if(Prog_Sync)
			begin
			
				case(selector)
				
					BASE_ADD: BASE_VALUE = (Prog_Sync !== 4'd0) ? Prog_Sync : BASE_DEFAULT;
					EXTD_ADD: EXTD_VALUE = (Prog_Sync !== 4'd0) ? Prog_Sync : EXTD_DEFAULT;
					YELL_ADD: YELL_VALUE = (Prog_Sync !== 4'd0) ? Prog_Sync : YELL_DEFAULT;
					
					default:														
						begin
							BASE_VALUE = BASE_DEFAULT;			
							EXTD_VALUE = EXTD_DEFAULT;
							YELL_VALUE = YELL_DEFAULT;
						end
				endcase
				
			end
			
		else
			begin
			
				case(interval)
					BASE_ADD: value <= BASE_VALUE;
					EXTD_ADD: value <= EXTD_VALUE;
					YELL_ADD: value <= YELL_VALUE;
				
					default:
						value <= 4'd15;										
				endcase																	
			
			end
	end
	
endmodule


//////////////////////////////////////////////////////////////////////////
////////////////   timer    //////////////////////////////////////////////
//////////////////////////////////////////////////////////////////////////

module timer (Hz1_enable, value, start_timer, Reset_Sync, expired);
  
  input[3:0] value;
  input Hz1_enable, start_timer, Reset_Sync;  
  output expired;
  reg expired;
  
  reg start_flag = 0;
  reg [3:0] counter = 4'b0000;

  
 
  always @(posedge Hz1_enable, Reset_Sync, negedge Hz1_enable)
    begin 
     if (Reset_Sync == 1)
      begin
       expired = 0;
       counter = 4'b0000;
       start_flag = 0;
     end
     else if (counter == value - 1) begin
         expired = 1;
         counter = 4'b0000;
         start_flag = 0;
     end
     else if (start_timer == 1 && start_flag == 0) begin
         start_flag = 1;
         expired = 0;
     end 
     else if (start_flag == 1) begin
         counter = counter + 4'b0001;
         expired = 0;
     end
     else begin
         expired = 0;
     end
    end
endmodule

////////////////////////////////////////////////////////////////
////////////////// Walk_Register   /////////////////////////////
////////////////////////////////////////////////////////////////

module Walk_Register(clk, WR_Reset, WR_Sync, WR_Status);
  
  input clk, WR_Reset, WR_Sync;
  output reg WR_Status;
  reg walk_reg;
  
  always @ (posedge clk, WR_Sync)
  begin
      if (WR_Sync == 1) begin
          walk_reg = 1;
          WR_Status = walk_reg;
      end
      else if (WR_Reset == 1) begin
          walk_reg = 0;
          WR_Status = walk_reg;
      end
  end
endmodule

Full design/fulldesign_testbench.v
//////////////////////////////////////////////////////////////////////////////////
//////////////         E/15/335 - fulldesign_testbench                 ///////////
//////////////     EE587 : Digital System Design and Synthesis   /////////////////
//////////////                  Assignment                        ////////////////
//////////////////////////////////////////////////////////////////////////////////

`timescale 1ms/1ms
`include "fulldesign.v"

module fulldesign_testbench;

reg clk,Reset,Sensor,Walk_Request,Reprogram;
reg [1:0] selector;
reg [3:0] time_value;
input[3:0] Prog_Sync;
input[1:0] interval;

wire [3:0] value;
wire [6:0] LEDs;
wire Hz1_enable,Reset_Sync, WR_Sync, Prog_Sync, Sensor_Sync,expired,WR_Status;
wire Rm,Ym,Gm,Rs,Ys,Gs,Walk, WR_Reset, start_timer;

Divider shezdiv (clk, Hz1_enable);

synchronizer shezsynch (clk, Reprogram, Walk_Request, Sensor, Reset, Reset_Sync, Sensor_Sync, WR_Sync, Prog_Sync);

Walk_Register shezWR (clk, WR_Reset, WR_Sync, WR_Status);

TimeParameters shezTM (selector, interval, Prog_Sync,time_value, value, clk, Reset_Sync);

timer sheztim (Hz1_enable, value, start_timer, Reset_Sync, expired);

LED_lights shezLED  (LEDs, Rm,Ym,Gm,Rs,Ys,Gs,Walk);

FSM shezFSM (Sensor_Sync, WR_Status, Prog_Sync, expired, WR_Reset, interval, start_timer, LEDs, clk, Reset_Sync);

initial begin
    $dumpfile("fulldesign.vcd");
    $dumpvars(0,fulldesign_testbench);

    clk = 0;
    Reset = 0;
    Sensor = 0;
    Reprogram = 0;

    #3000 

    Walk_Request = 1;
    #5 

    Walk_Request = 0;
    #1300 

    Sensor = 1;
    #15000 

    Walk_Request = 1;
    #5 
    
    Walk_Request = 0;
    #22000 

    Sensor = 0;
    #10000

    Walk_Request = 1;
    #5

    Walk_Request = 0;
    #20000

    Sensor = 1;
    #20

    #30000 $finish();
end

initial forever 
#0.5 clk =~ clk;
    
endmodule

Full design/fulldesign.vcd
$date
	Wed May 26 19:30:21 2021
$end
$version
	Icarus Verilog
$end
$timescale
	1ms
$end
$scope module fulldesign_testbench $end
$var wire 4 ! value [3:0] $end
$var wire 1 " start_timer $end
$var wire 2 # interval [1:0] $end
$var wire 1 $ expired $end
$var wire 1 % Ys $end
$var wire 1 & Ym $end
$var wire 1 ' Walk $end
$var wire 1 ( WR_Sync $end
$var wire 1 ) WR_Status $end
$var wire 1 * WR_Reset $end
$var wire 1 + Sensor_Sync $end
$var wire 1 , Rs $end
$var wire 1 - Rm $end
$var wire 1 . Reset_Sync $end
$var wire 4 / Prog_Sync [3:0] $end
$var wire 7 0 LEDs [6:0] $end
$var wire 1 1 Hz1_enable $end
$var wire 1 2 Gs $end
$var wire 1 3 Gm $end
$var reg 1 4 Reprogram $end
$var reg 1 5 Reset $end
$var reg 1 6 Sensor $end
$var reg 1 7 Walk_Request $end
$var reg 1 8 clk $end
$var reg 2 9 selector [1:0] $end
$var reg 4 : time_value [3:0] $end
$scope module shezFSM $end
$var wire 1 8 clk $end
$var wire 1 $ expired $end
$var wire 1 ) WR_Status $end
$var wire 1 + Sensor_Sync $end
$var wire 1 . Reset_Sync $end
$var wire 4 ; Prog_Sync [3:0] $end
$var reg 7 < LEDs [6:0] $end
$var reg 1 * WR_Reset $end
$var reg 2 = interval [1:0] $end
$var reg 1 " start_timer $end
$var reg 3 > state [2:0] $end
$upscope $end
$scope module shezLED $end
$var wire 7 ? LEDs [6:0] $end
$var reg 1 3 Gm $end
$var reg 1 2 Gs $end
$var reg 1 - Rm $end
$var reg 1 , Rs $end
$var reg 1 ' Walk $end
$var reg 1 & Ym $end
$var reg 1 % Ys $end
$upscope $end
$scope module shezTM $end
$var wire 1 8 clk $end
$var wire 2 @ interval [1:0] $end
$var wire 2 A selector [1:0] $end
$var wire 4 B time_value [3:0] $end
$var wire 1 . Reset_Sync $end
$var wire 4 C Prog_Sync [3:0] $end
$var reg 4 D BASE_VALUE [3:0] $end
$var reg 4 E EXTD_VALUE [3:0] $end
$var reg 4 F YELL_VALUE [3:0] $end
$var reg 4 G value [3:0] $end
$upscope $end
$scope module shezWR $end
$var wire 1 * WR_Reset $end
$var wire 1 8 clk $end
$var wire 1 ( WR_Sync $end
$var reg 1 ) WR_Status $end
$var reg 1 H walk_reg $end
$upscope $end
$scope module shezdiv $end
$var wire 1 8 clk $end
$var reg 1 1 Hz1_enable $end
$var reg 10 I counter [9:0] $end
$upscope $end
$scope module shezsynch $end
$var wire 1 4 Reprogram $end
$var wire 1 5 Reset $end
$var wire 1 6 Sensor $end
$var wire 1 7 Walk_Request $end
$var wire 1 8 clk $end
$var reg 4 J Prog_Sync [3:0] $end
$var reg 1 . Reset_Sync $end
$var reg 1 + Sensor_Sync $end
$var reg 1 ( WR_Sync $end
$upscope $end
$scope module sheztim $end
$var wire 1 1 Hz1_enable $end
$var wire 1 . Reset_Sync $end
$var wire 1 " start_timer $end
$var wire 4 K value [3:0] $end
$var reg 4 L counter [3:0] $end
$var reg 1 $ expired $end
$var reg 1 M start_flag $end
$upscope $end
$upscope $end
$enddefinitions $end
#0
$dumpvars
0M
b0 L
bx K
bx J
b1 I
xH
bx G
b10 F
b11 E
b110 D
bx C
bx B
bx A
b0 @
bx ?
b1 >
b0 =
bx <
bx ;
bx :
bx 9
08
x7
06
05
04
x3
x2
01
bx 0
bx /
x.
x-
x,
x+
0*
x)
x(
x'
x&
x%
x$
b0 #
1"
bx !
$end
#1
b11 >
b10 #
b10 =
b10 @
b110 !
b110 G
b110 K
0$
1M
1"
b0 /
b0 ;
b0 C
b0 J
0+
0.
b10 I
18
#2
0'
02
0%
1,
03
1&
0-
b101000 0
b101000 <
b101000 ?
0"
b11 I
08
#3
b10 !
b10 G
b10 K
b100 I
18
#4
b101 I
08
#5
b110 I
18
#6
b111 I
08
#7
b1000 I
18
#8
b1001 I
08
#9
b1010 I
18
#10
b1011 I
08
#11
b1100 I
18
#12
b1101 I
08
#13
b1110 I
18
#14
b1111 I
08
#15
b10000 I
18
#16
b10001 I
08
#17
b10010 I
18
#18
b10011 I
08
#19
b10100 I
18
#20
b10101 I
08
#21
b10110 I
18
#22
b10111 I
08
#23
b11000 I
18
#24
b11001 I
08
#25
b11010 I
18
#26
b11011 I
08
#27
b11100 I
18
#28
b11101 I
08
#29
b11110 I
18
#30
b11111 I
08
#31
b100000 I
18
#32
b100001 I
08
#33
b100010 I
18
#34
b100011 I
08
#35
b100100 I
18
#36
b100101 I
08
#37
b100110 I
18
#38
b100111 I
08
#39
b101000 I
18
#40
b101001 I
08
#41
b101010 I
18
#42
b101011 I
08
#43
b101100 I
18
#44
b101101 I
08
#45
b101110 I
18
#46
b101111 I
08
#47
b110000 I
18
#48
b110001 I
08
#49
b110010 I
18
#50
b110011 I
08
#51
b110100 I
18
#52
b110101 I
08
#53
b110110 I
18
#54
b110111 I
08
#55
b111000 I
18
#56
b111001 I
08
#57
b111010 I
18
#58
b111011 I
08
#59
b111100 I
18
#60
b111101 I
08
#61
b111110 I
18
#62
b111111 I
08
#63
b1000000 I
18
#64
b1000001 I
08
#65
b1000010 I
18
#66
b1000011 I
08
#67
b1000100 I
18
#68
b1000101 I
08
#69
b1000110 I
18
#70
b1000111 I
08
#71
b1001000 I
18
#72
b1001001 I
08
#73
b1001010 I
18
#74
b1001011 I
08
#75
b1001100 I
18
#76
b1001101 I
08
#77
b1001110 I
18
#78
b1001111 I
08
#79
b1010000 I
18
#80
b1010001 I
08
#81
b1010010 I
18
#82
b1010011 I
08
#83
b1010100 I
18
#84
b1010101 I
08
#85
b1010110 I
18
#86
b1010111 I
08
#87
b1011000 I
18
#88
b1011001 I
08
#89
b1011010 I
18
#90
b1011011 I
08
#91
b1011100 I
18
#92
b1011101 I
08
#93
b1011110 I
18
#94
b1011111 I
08
#95
b1100000 I
18
#96
b1100001 I
08
#97
b1100010 I
18
#98
b1100011 I
08
#99
b1100100 I
18
#100
b1100101 I
08
#101
b1100110 I
18
#102
b1100111 I
08
#103
b1101000 I
18
#104
b1101001 I
08
#105
b1101010 I
18
#106
b1101011 I
08
#107
b1101100 I
18
#108
b1101101 I
08
#109
b1101110 I
18
#110
b1101111 I
08
#111
b1110000 I
18
#112
b1110001 I
08
#113
b1110010 I
18
#114
b1110011 I
08
#115
b1110100 I
18
#116
b1110101 I
08
#117
b1110110 I
18
#118
b1110111 I
08
#119
b1111000 I
18
#120
b1111001 I
08
#121
b1111010 I
18
#122
b1111011 I
08
#123
b1111100 I
18
#124
b1111101 I
08
#125
b1111110 I
18
#126
b1111111 I
08
#127
b10000000 I
18
#128
b10000001 I
08
#129
b10000010 I
18
#130
b10000011 I
08
#131
b10000100 I
18
#132
b10000101 I
08
#133
b10000110 I
18
#134
b10000111 I
08
#135
b10001000 I
18
#136
b10001001 I
08
#137
b10001010 I
18
#138
b10001011 I
08
#139
b10001100 I
18
#140
b10001101 I
08
#141
b10001110 I
18
#142
b10001111 I
08
#143
b10010000 I
18
#144
b10010001 I
08
#145
b10010010 I
18
#146
b10010011 I
08
#147
b10010100 I
18
#148
b10010101 I
08
#149
b10010110 I
18
#150
b10010111 I
08
#151
b10011000 I
18
#152
b10011001 I
08
#153
b10011010 I
18
#154
b10011011 I
08
#155
b10011100 I
18
#156
b10011101 I
08
#157
b10011110 I
18
#158
b10011111 I
08
#159
b10100000 I
18
#160
b10100001 I
08
#161
b10100010 I
18
#162
b10100011 I
08
#163
b10100100 I
18
#164
b10100101 I
08
#165
b10100110 I
18
#166
b10100111 I
08
#167
b10101000 I
18
#168
b10101001 I
08
#169
b10101010 I
18
#170
b10101011 I
08
#171
b10101100 I
18
#172
b10101101 I
08
#173
b10101110 I
18
#174
b10101111 I
08
#175
b10110000 I
18
#176
b10110001 I
08
#177
b10110010 I
18
#178
b10110011 I
08
#179
b10110100 I
18
#180
b10110101 I
08
#181
b10110110 I
18
#182
b10110111 I
08
#183
b10111000 I
18
#184
b10111001 I
08
#185
b10111010 I
18
#186
b10111011 I
08
#187
b10111100 I
18
#188
b10111101 I
08
#189
b10111110 I
18
#190
b10111111 I
08
#191
b11000000 I
18
#192
b11000001 I
08
#193
b11000010 I
18
#194
b11000011 I
08
#195
b11000100 I
18
#196
b11000101 I
08
#197
b11000110 I
18
#198
b11000111 I
08
#199
b11001000 I
18
#200
b11001001 I
08
#201
b11001010 I
18
#202
b11001011 I
08
#203
b11001100 I
18
#204
b11001101 I
08
#205
b11001110 I
18
#206
b11001111 I
08
#207
b11010000 I
18
#208
b11010001 I
08
#209
b11010010 I
18
#210
b11010011 I
08
#211
b11010100 I
18
#212
b11010101 I
08
#213
b11010110 I
18
#214
b11010111 I
08
#215
b11011000 I
18
#216
b11011001 I
08
#217
b11011010 I
18
#218
b11011011 I
08
#219
b11011100 I
18
#220
b11011101 I
08
#221
b11011110 I
18
#222
b11011111 I
08
#223
b11100000 I
18
#224
b11100001 I
08
#225
b11100010 I
18
#226
b11100011 I
08
#227
b11100100 I
18
#228
b11100101 I
08
#229
b11100110 I
18
#230
b11100111 I
08
#231
b11101000 I
18
#232
b11101001 I
08
#233
b11101010 I
18
#234
b11101011 I
08
#235
b11101100 I
18
#236
b11101101 I
08
#237
b11101110 I
18
#238
b11101111 I
08
#239
b11110000 I
18
#240
b11110001 I
08
#241
b11110010 I
18
#242
b11110011 I
08
#243
b11110100 I
18
#244
b11110101 I
08
#245
b11110110 I
18
#246
b11110111 I
08
#247
b11111000 I
18
#248
b11111001 I
08
#249
b11111010 I
18
#250
b11111011 I
08
#251
b11111100 I
18
#252
b11111101 I
08
#253
b11111110 I
18
#254
b11111111 I
08
#255
b100000000 I
18
#256
b100000001 I
08
#257
b100000010 I
18
#258
b100000011 I
08
#259
b100000100 I
18
#260
b100000101 I
08
#261
b100000110 I
18
#262
b100000111 I
08
#263
b100001000 I
18
#264
b100001001 I
08
#265
b100001010 I
18
#266
b100001011 I
08
#267
b100001100 I
18
#268
b100001101 I
08
#269
b100001110 I
18
#270
b100001111 I
08
#271
b100010000 I
18
#272
b100010001 I
08
#273
b100010010 I
18
#274
b100010011 I
08
#275
b100010100 I
18
#276
b100010101 I
08
#277
b100010110 I
18
#278
b100010111 I
08
#279
b100011000 I
18
#280
b100011001 I
08
#281
b100011010 I
18
#282
b100011011 I
08
#283
b100011100 I
18
#284
b100011101 I
08
#285
b100011110 I
18
#286
b100011111 I
08
#287
b100100000 I
18
#288
b100100001 I
08
#289
b100100010 I
18
#290
b100100011 I
08
#291
b100100100 I
18
#292
b100100101 I
08
#293
b100100110 I
18
#294
b100100111 I
08
#295
b100101000 I
18
#296
b100101001 I
08
#297
b100101010 I
18
#298
b100101011 I
08
#299
b100101100 I
18
#300
b100101101 I
08
#301
b100101110 I
18
#302
b100101111 I
08
#303
b100110000 I
18
#304
b100110001 I
08
#305
b100110010 I
18
#306
b100110011 I
08
#307
b100110100 I
18
#308
b100110101 I
08
#309
b100110110 I
18
#310
b100110111 I
08
#311
b100111000 I
18
#312
b100111001 I
08
#313
b100111010 I
18
#314
b100111011 I
08
#315
b100111100 I
18
#316
b100111101 I
08
#317
b100111110 I
18
#318
b100111111 I
08
#319
b101000000 I
18
#320
b101000001 I
08
#321
b101000010 I
18
#322
b101000011 I
08
#323
b101000100 I
18
#324
b101000101 I
08
#325
b101000110 I
18
#326
b101000111 I
08
#327
b101001000 I
18
#328
b101001001 I
08
#329
b101001010 I
18
#330
b101001011 I
08
#331
b101001100 I
18
#332
b101001101 I
08
#333
b101001110 I
18
#334
b101001111 I
08
#335
b101010000 I
18
#336
b101010001 I
08
#337
b101010010 I
18
#338
b101010011 I
08
#339
b101010100 I
18
#340
b101010101 I
08
#341
b101010110 I
18
#342
b101010111 I
08
#343
b101011000 I
18
#344
b101011001 I
08
#345
b101011010 I
18
#346
b101011011 I
08
#347
b101011100 I
18
#348
b101011101 I
08
#349
b101011110 I
18
#350
b101011111 I
08
#351
b101100000 I
18
#352
b101100001 I
08
#353
b101100010 I
18
#354
b101100011 I
08
#355
b101100100 I
18
#356
b101100101 I
08
#357
b101100110 I
18
#358
b101100111 I
08
#359
b101101000 I
18
#360
b101101001 I
08
#361
b101101010 I
18
#362
b101101011 I
08
#363
b101101100 I
18
#364
b101101101 I
08
#365
b101101110 I
18
#366
b101101111 I
08
#367
b101110000 I
18
#368
b101110001 I
08
#369
b101110010 I
18
#370
b101110011 I
08
#371
b101110100 I
18
#372
b101110101 I
08
#373
b101110110 I
18
#374
b101110111 I
08
#375
b101111000 I
18
#376
b101111001 I
08
#377
b101111010 I
18
#378
b101111011 I
08
#379
b101111100 I
18
#380
b101111101 I
08
#381
b101111110 I
18
#382
b101111111 I
08
#383
b110000000 I
18
#384
b110000001 I
08
#385
b110000010 I
18
#386
b110000011 I
08
#387
b110000100 I
18
#388
b110000101 I
08
#389
b110000110 I
18
#390
b110000111 I
08
#391
b110001000 I
18
#392
b110001001 I
08
#393
b110001010 I
18
#394
b110001011 I
08
#395
b110001100 I
18
#396
b110001101 I
08
#397
b110001110 I
18
#398
b110001111 I
08
#399
b110010000 I
18
#400
b110010001 I
08
#401
b110010010 I
18
#402
b110010011 I
08
#403
b110010100 I
18
#404
b110010101 I
08
#405
b110010110 I
18
#406
b110010111 I
08
#407
b110011000 I
18
#408
b110011001 I
08
#409
b110011010 I
18
#410
b110011011 I
08
#411
b110011100 I
18
#412
b110011101 I
08
#413
b110011110 I
18
#414
b110011111 I
08
#415
b110100000 I
18
#416
b110100001 I
08
#417
b110100010 I
18
#418
b110100011 I
08
#419
b110100100 I
18
#420
b110100101 I
08
#421
b110100110 I
18
#422
b110100111 I
08
#423
b110101000 I
18
#424
b110101001 I
08
#425
b110101010 I
18
#426
b110101011 I
08
#427
b110101100 I
18
#428
b110101101 I
08
#429
b110101110 I
18
#430
b110101111 I
08
#431
b110110000 I
18
#432
b110110001 I
08
#433
b110110010 I
18
#434
b110110011 I
08
#435
b110110100 I
18
#436
b110110101 I
08
#437
b110110110 I
18
#438
b110110111 I
08
#439
b110111000 I
18
#440
b110111001 I
08
#441
b110111010 I
18
#442
b110111011 I
08
#443
b110111100 I
18
#444
b110111101 I
08
#445
b110111110 I
18
#446
b110111111 I
08
#447
b111000000 I
18
#448
b111000001 I
08
#449
b111000010 I
18
#450
b111000011 I
08
#451
b111000100 I
18
#452
b111000101 I
08
#453
b111000110 I
18
#454
b111000111 I
08
#455
b111001000 I
18
#456
b111001001 I
08
#457
b111001010 I
18
#458
b111001011 I
08
#459
b111001100 I
18
#460
b111001101 I
08
#461
b111001110 I
18
#462
b111001111 I
08
#463
b111010000 I
18
#464
b111010001 I
08
#465
b111010010 I
18
#466
b111010011 I
08
#467
b111010100 I
18
#468
b111010101 I
08
#469
b111010110 I
18
#470
b111010111 I
08
#471
b111011000 I
18
#472
b111011001 I
08
#473
b111011010 I
18
#474
b111011011 I
08
#475
b111011100 I
18
#476
b111011101 I
08
#477
b111011110 I
18
#478
b111011111 I
08
#479
b111100000 I
18
#480
b111100001 I
08
#481
b111100010 I
18
#482
b111100011 I
08
#483
b111100100 I
18
#484
b111100101 I
08
#485
b111100110 I
18
#486
b111100111 I
08
#487
b111101000 I
18
#488
b111101001 I
08
#489
b111101010 I
18
#490
b111101011 I
08
#491
b111101100 I
18
#492
b111101101 I
08
#493
b111101110 I
18
#494
b111101111 I
08
#495
b111110000 I
18
#496
b111110001 I
08
#497
b111110010 I
18
#498
b111110011 I
08
#499
b111110100 I
18
#500
b111110101 I
08
#501
b111110110 I
18
#502
b111110111 I
08
#503
b111111000 I
18
#504
b111111001 I
08
#505
b111111010 I
18
#506
b111111011 I
08
#507
b111111100 I
18
#508
b111111101 I
08
#509
b111111110 I
18
#510
b111111111 I
08
#511
b1000000000 I
18
#512
b1000000001 I
08
#513
b1000000010 I
18
#514
b1000000011 I
08
#515
b1000000100 I
18
#516
b1000000101 I
08
#517
b1000000110 I
18
#518
b1000000111 I
08
#519
b1000001000 I
18
#520
b1000001001 I
08
#521
b1000001010 I
18
#522
b1000001011 I
08
#523
b1000001100 I
18
#524
b1000001101 I
08
#525
b1000001110 I
18
#526
b1000001111 I
08
#527
b1000010000 I
18
#528
b1000010001 I
08
#529
b1000010010 I
18
#530
b1000010011 I
08
#531
b1000010100 I
18
#532
b1000010101 I
08
#533
b1000010110 I
18
#534
b1000010111 I
08
#535
b1000011000 I
18
#536
b1000011001 I
08
#537
b1000011010 I
18
#538
b1000011011 I
08
#539
b1000011100 I
18
#540
b1000011101 I
08
#541
b1000011110 I
18
#542
b1000011111 I
08
#543
b1000100000 I
18
#544
b1000100001 I
08
#545
b1000100010 I
18
#546
b1000100011 I
08
#547
b1000100100 I
18
#548
b1000100101 I
08
#549
b1000100110 I
18
#550
b1000100111 I
08
#551
b1000101000 I
18
#552
b1000101001 I
08
#553
b1000101010 I
18
#554
b1000101011 I
08
#555
b1000101100 I
18
#556
b1000101101 I
08
#557
b1000101110 I
18
#558
b1000101111 I
08
#559
b1000110000 I
18
#560
b1000110001 I
08
#561
b1000110010 I
18
#562
b1000110011 I
08
#563
b1000110100 I
18
#564
b1000110101 I
08
#565
b1000110110 I
18
#566
b1000110111 I
08
#567
b1000111000 I
18
#568
b1000111001 I
08
#569
b1000111010 I
18
#570
b1000111011 I
08
#571
b1000111100 I
18
#572
b1000111101 I
08
#573
b1000111110 I
18
#574
b1000111111 I
08
#575
b1001000000 I
18
#576
b1001000001 I
08
#577
b1001000010 I
18
#578
b1001000011 I
08
#579
b1001000100 I
18
#580
b1001000101 I
08
#581
b1001000110 I
18
#582
b1001000111 I
08
#583
b1001001000 I
18
#584
b1001001001 I
08
#585
b1001001010 I
18
#586
b1001001011 I
08
#587
b1001001100 I
18
#588
b1001001101 I
08
#589
b1001001110 I
18
#590
b1001001111 I
08
#591
b1001010000 I
18
#592
b1001010001 I
08
#593
b1001010010 I
18
#594
b1001010011 I
08
#595
b1001010100 I
18
#596
b1001010101 I
08
#597
b1001010110 I
18
#598
b1001010111 I
08
#599
b1001011000 I
18
#600
b1001011001 I
08
#601
b1001011010 I
18
#602
b1001011011 I
08
#603
b1001011100 I
18
#604
b1001011101 I
08
#605
b1001011110 I
18
#606
b1001011111 I
08
#607
b1001100000 I
18
#608
b1001100001 I
08
#609
b1001100010 I
18
#610
b1001100011 I
08
#611
b1001100100 I
18
#612
b1001100101 I
08
#613
b1001100110 I
18
#614
b1001100111 I
08
#615
b1001101000 I
18
#616
b1001101001 I
08
#617
b1001101010 I
18
#618
b1001101011 I
08
#619
b1001101100 I
18
#620
b1001101101 I
08
#621
b1001101110 I
18
#622
b1001101111 I
08
#623
b1001110000 I
18
#624
b1001110001 I
08
#625
b1001110010 I
18
#626
b1001110011 I
08
#627
b1001110100 I
18
#628
b1001110101 I
08
#629
b1001110110 I
18
#630
b1001110111 I
08
#631
b1001111000 I
18
#632
b1001111001 I
08
#633
b1001111010 I
18
#634
b1001111011 I
08
#635
b1001111100 I
18
#636
b1001111101 I
08
#637
b1001111110 I
18
#638
b1001111111 I
08
#639
b1010000000 I
18
#640
b1010000001 I
08
#641
b1010000010 I
18
#642
b1010000011 I
08
#643
b1010000100 I
18
#644
b1010000101 I
08
#645
b1010000110 I
18
#646
b1010000111 I
08
#647
b1010001000 I
18
#648
b1010001001 I
08
#649
b1010001010 I
18
#650
b1010001011 I
08
#651
b1010001100 I
18
#652
b1010001101 I
08
#653
b1010001110 I
18
#654
b1010001111 I
08
#655
b1010010000 I
18
#656
b1010010001 I
08
#657
b1010010010 I
18
#658
b1010010011 I
08
