Previous submissions/FSM/FSM.v
`timescale 1ns / 1ps

module FSM(Sensor_Sync, WR, Prog_Sync, expired, WR_Reset, interval, start_timer, LEDs, clk, Reset);
	
    input Sensor_Sync, WR, Prog_Sync, expired, clk, Reset;
	output WR_Reset, start_timer;
    output[6:0] LEDs;
	output[1:0] interval;
	
	reg WR_Reset, start_timer;
    reg[6:0] LEDs = 7'b0011000;
    reg[1:0] interval = 2'b00;
	reg[2:0] state = 3'd0;
	
	parameter START_MAIN_GREEN = 0;
	parameter CONT_MAIN_GREEN_NO_TRAFFIC = 1;
	parameter CONT_MAIN_GREEN_TRAFFIC = 2;
	parameter MAIN_YELLOW = 3;
	parameter PEDESTRIAN_WALK = 4;
	parameter START_SIDE_GREEN = 5;
	parameter CONT_SIDE_GREEN_TRAFFIC = 6;
	parameter SIDE_YELLOW = 7;

	parameter BASE_ADD = 2'b00 ;
	parameter EXT_ADD = 2'b01 ;
	parameter YEL_ADD = 2'b10 ;
	
	always @ ( posedge clk )
	begin
	
		start_timer = 0;					
		WR_Reset = 0;

      if ( Reset || Prog_Sync)
			begin
			start_timer = 1;
			interval = BASE_ADD ;
			state = START_MAIN_GREEN ;
			end
			
		else if (~ expired )
			begin
			case ( state )
				START_MAIN_GREEN, CONT_MAIN_GREEN_NO_TRAFFIC, CONT_MAIN_GREEN_TRAFFIC :
					LEDs = 7'b0011000;	// bits represent Rm,Ym,Gm,Rs,Ys,Gs,Walk from left to right of the bits 
            
				MAIN_YELLOW :
					LEDs = 7'b0101000;	

				PEDESTRIAN_WALK :
					LEDs = 7'b1001001;	 

				START_SIDE_GREEN, CONT_SIDE_GREEN_TRAFFIC :
					LEDs = 7'b1000010;	

				SIDE_YELLOW :
					LEDs = 7'b1000100;	
			endcase
			end
		
		else
			begin
			
			start_timer = 1;

			case ( state )
				START_MAIN_GREEN :
					begin
                      if ( Sensor_Sync )
							begin
								
								interval = EXT_ADD ;
								state = CONT_MAIN_GREEN_TRAFFIC ;
							end
						else
							begin
								interval = BASE_ADD ;
								state = CONT_MAIN_GREEN_NO_TRAFFIC ;
							end
					end

				CONT_MAIN_GREEN_NO_TRAFFIC,CONT_MAIN_GREEN_TRAFFIC :
					begin
						interval= YEL_ADD ;
						state = MAIN_YELLOW ;
					end

				MAIN_YELLOW :
					begin
						
                      if ( WR )
							begin
								
								interval= EXT_ADD ;
								state = PEDESTRIAN_WALK ;
							end
						else
							begin
								interval = BASE_ADD ;
								state = START_SIDE_GREEN ;
							end
					end

				PEDESTRIAN_WALK :
					begin
				
						interval= BASE_ADD ;
						state = START_SIDE_GREEN ;
						WR_Reset = 1;
					end

				START_SIDE_GREEN :
					begin
                      if ( Sensor_Sync )
							begin
								interval = EXT_ADD ;
								state = CONT_SIDE_GREEN_TRAFFIC ;
							end
						else
							begin
								interval = YEL_ADD ;
								state  = SIDE_YELLOW ;

							end
					end

				CONT_SIDE_GREEN_TRAFFIC :
					begin
						interval = YEL_ADD ;
						state = SIDE_YELLOW ;
					end

				SIDE_YELLOW :
					begin
						interval = BASE_ADD ;
						state = START_MAIN_GREEN ;
					end

			endcase
			end
			
	end
	
endmodule

Previous submissions/FSM/FSM_testbench.v
`timescale 1ns / 1ps

`include "FSM.v"

module FSM_testbench;

	
	reg Sensor_Sync;
	reg WR;
	reg Prog_Sync;
	reg expired;
	reg clk;
	reg Reset;

	wire WR_Reset;
	wire [1:0] interval;
	wire start_timer;
    wire [6:0] LEDs;

	
	FSM t1(Sensor_Sync, WR, Prog_Sync, expired, WR_Reset, interval, start_timer, LEDs, clk, Reset);
		

	initial begin
		forever #10 clk = ~clk;
	end

	initial begin
		
      
      $dumpfile("FSM_testbench.vcd");
      $dumpvars(0,FSM_testbench);
    
		Sensor_Sync = 0;
		WR = 0;
		Prog_Sync = 0;
		expired = 0;
		clk = 0;
		Reset = 0;

		#90;
        
		
	    Reset = 1;
		WR = 1;
		
		#20
		Reset = 0;
		
		#120
		expired = 1;
		
		#20
		expired = 0;
		
		#120
		expired = 1;
		
		#20
		expired = 0;
		
		#40
		expired = 1;
		
		#20
		expired = 0;
		
		#60
		expired = 1;
		
		#20
		expired = 0;
		
		#40
		expired = 1;
		
		#20
		expired = 0;
		
		#20
		Sensor_Sync = 1;

		#100
		expired = 1;
		
		#20
		expired = 0;
		
		#60
		expired = 1;
		
		#20
		expired = 0;
		
		#120
		expired = 1;
		
		#20
		expired = 0;
       #20 $finish();
		
	end
      
endmodule

Previous submissions/FSM/FSM_testbench.vcd
$date
	Mon May 24 23:37:24 2021
$end
$version
	Icarus Verilog
$end
$timescale
	1ps
$end
$scope module FSM_testbench $end
$var wire 1 ! start_timer $end
$var wire 2 " interval [1:0] $end
$var wire 1 # WR_Reset $end
$var wire 7 $ LEDs [6:0] $end
$var reg 1 % Prog_Sync $end
$var reg 1 & Reset $end
$var reg 1 ' Sensor_Sync $end
$var reg 1 ( WR $end
$var reg 1 ) clk $end
$var reg 1 * expired $end
$scope module t1 $end
$var wire 1 % Prog_Sync $end
$var wire 1 & Reset $end
$var wire 1 ' Sensor_Sync $end
$var wire 1 ( WR $end
$var wire 1 ) clk $end
$var wire 1 * expired $end
$var reg 7 + LEDs [6:0] $end
$var reg 1 # WR_Reset $end
$var reg 2 , interval [1:0] $end
$var reg 1 ! start_timer $end
$var reg 3 - state [2:0] $end
$upscope $end
$upscope $end
$enddefinitions $end
#0
$dumpvars
b0 -
b0 ,
b11000 +
0*
0)
0(
0'
0&
0%
b11000 $
x#
b0 "
x!
$end
#10000
0#
0!
1)
#20000
0)
#30000
1)
#40000
0)
#50000
1)
#60000
0)
#70000
1)
#80000
0)
#90000
1!
1)
1(
1&
#100000
0)
#110000
0!
1)
0&
#120000
0)
#130000
1)
#140000
0)
#150000
1)
#160000
0)
#170000
1)
#180000
0)
#190000
1)
#200000
0)
#210000
1)
#220000
0)
#230000
b1 -
1!
1)
1*
#240000
0)
#250000
0!
1)
0*
#260000
0)
#270000
1)
#280000
0)
#290000
1)
#300000
0)
#310000
1)
#320000
0)
#330000
1)
#340000
0)
#350000
1)
#360000
0)
#370000
b11 -
b10 "
b10 ,
1!
1)
1*
#380000
0)
#390000
b101000 $
b101000 +
0!
1)
0*
#400000
0)
#410000
1)
#420000
0)
#430000
b100 -
b1 "
b1 ,
1!
1)
1*
#440000
0)
#450000
b1001001 $
b1001001 +
0!
1)
0*
#460000
0)
#470000
1)
#480000
0)
#490000
1)
#500000
0)
#510000
1#
b101 -
b0 "
b0 ,
1!
1)
1*
#520000
0)
#530000
b1000010 $
b1000010 +
0#
0!
1)
0*
#540000
0)
#550000
1)
#560000
0)
#570000
b111 -
b10 "
b10 ,
1!
1)
1*
#580000
0)
#590000
b1000100 $
b1000100 +
0!
1)
0*
#600000
0)
#610000
1)
1'
#620000
0)
#630000
1)
#640000
0)
#650000
1)
#660000
0)
#670000
1)
#680000
0)
#690000
1)
#700000
0)
#710000
b0 -
b0 "
b0 ,
1!
1)
1*
#720000
0)
#730000
b11000 $
b11000 +
0!
1)
0*
#740000
0)
#750000
1)
#760000
0)
#770000
1)
#780000
0)
#790000
b10 -
b1 "
b1 ,
1!
1)
1*
#800000
0)
#810000
0!
1)
0*
#820000
0)
#830000
1)
#840000
0)
#850000
1)
#860000
0)
#870000
1)
#880000
0)
#890000
1)
#900000
0)
#910000
1)
#920000
0)
#930000
b11 -
b10 "
b10 ,
1!
1)
1*
#940000
0)
#950000
b101000 $
b101000 +
0!
1)
0*
